setup.py
dist/pyvb-0.0.1-py2.5.egg
dist/pyvb-0.0.2-py2.5.egg
dist/pyvb-0.0.2.tar.gz
src/pyvb/__init__.py
src/pyvb/command.py
src/pyvb/constants.py
src/pyvb/dvd.py
src/pyvb/exception.py
src/pyvb/hdd.py
src/pyvb/ostype.py
src/pyvb/parser.py
src/pyvb/server.py
src/pyvb/sharedfolder.py
src/pyvb/state.py
src/pyvb/vb.py
src/pyvb/vm.py
src/pyvb.egg-info/PKG-INFO
src/pyvb.egg-info/SOURCES.txt
src/pyvb.egg-info/dependency_links.txt
src/pyvb.egg-info/entry_points.txt
src/pyvb.egg-info/not-zip-safe
src/pyvb.egg-info/requires.txt
src/pyvb.egg-info/top_level.txt