Metadata-Version: 1.0
Name: pyvb
Version: 0.0.10
Summary: Python VirtualBox API.
Home-page: http://enomalism.com/api/pyvb/
Author: Adam Boduch
Author-email: adam@enomaly.com
License: GPL
Platform: UNKNOWN
